djmease
