Metadata-Version: 1.1
Name: django-mease
Version: 0.2.0
Summary: django-mease: Websocket integration made easy for Django
Home-page: https://github.com/florianpaquet/django-mease
Author: Florian PAQUET
Author-email: contact@florianpaquet.com
License: MIT
Platform: UNKNOWN
Classifier: Development Status :: 4 - Beta
Classifier: Environment :: Web Environment
Classifier: Framework :: Django
Classifier: Intended Audience :: Developers
Classifier: License :: OSI Approved :: MIT License
Classifier: Operating System :: OS Independent
Classifier: Programming Language :: Python
Classifier: Topic :: Internet :: WWW/HTTP :: Dynamic Content
Classifier: Topic :: Software Development :: Libraries :: Python Modules
